feature_suggestion_agent/__init__.py
feature_suggestion_agent/agent.py
feature_suggestion_agent/config.py
feature_suggestion_agent/constants.py
feature_suggestion_agent/models.py
feature_suggestion_agent-0.1.2.dist-info/METADATA
feature_suggestion_agent-0.1.2.dist-info/WHEEL
feature_suggestion_agent-0.1.2.dist-info/top_level.txt
feature_suggestion_agent-0.1.2.dist-info/RECORD
