Metadata-Version: 2.4
Name: feature-suggestion-agent
Version: 0.1.2
Summary: An intelligent agent for suggesting features for machine learning datasets
Author-email: StepFunction AI <team@stepfunction.ai>
License-Expression: MIT
Project-URL: Homepage, https://github.com/stepfnAI/feature_suggestion_agent
Project-URL: Issues, https://github.com/stepfnAI/feature_suggestion_agent/issues
Requires-Python: >=3.10
Requires-Dist: sfn-blueprint>=0.6.13
Requires-Dist: pandas
Requires-Dist: pydantic-settings
Provides-Extra: dev
Requires-Dist: pytest>=7.0.0; extra == "dev"
Requires-Dist: pytest-cov>=4.0.0; extra == "dev"
Requires-Dist: black>=23.0.0; extra == "dev"
Requires-Dist: flake8>=6.0.0; extra == "dev"
Requires-Dist: mypy>=1.0.0; extra == "dev"
